README.md
setup.cfg
setup.py
pytest_ec2/__init__.py
pytest_ec2/execute_test_case.py
pytest_ec2/pytest_ec2.py
pytest_ec2/pytest_slack.py
pytest_ec2.egg-info/PKG-INFO
pytest_ec2.egg-info/SOURCES.txt
pytest_ec2.egg-info/dependency_links.txt
pytest_ec2.egg-info/requires.txt
pytest_ec2.egg-info/top_level.txt