Metadata-Version: 1.1
Name: pytest-ec2
Version: 0.1
Summary: Pytest execution on EC2 instance
Home-page: https://github.com/randomlock/pytest_ec2
Author: abdullahhasan
Author-email: abdullahh546@gmail.com
License: MIT
Download-URL: https://github.com/randomlock/pytest_ec2/archive/0.1.tar.gz
Platform: UNKNOWN
Classifier: Development Status :: 3 - Alpha
Classifier: Intended Audience :: Developers
Classifier: Topic :: Software Development :: Build Tools
Classifier: License :: OSI Approved :: MIT License
Classifier: Programming Language :: Python :: 3
Classifier: Programming Language :: Python :: 3.4
Classifier: Programming Language :: Python :: 3.5
Classifier: Programming Language :: Python :: 3.6
